netilion_lab_api/__init__.py
netilion_lab_api/api_client.py
netilion_lab_api/configuration.py
netilion_lab_api/rest.py
netilion_lab_api/api/__init__.py
netilion_lab_api/api/add_on_api.py
netilion_lab_api/api/app_instance_api.py
netilion_lab_api/api/batch_api.py
netilion_lab_api/api/batch_status_api.py
netilion_lab_api/api/batch_type_api.py
netilion_lab_api/api/connected_asset_api.py
netilion_lab_api/api/connected_asset_config_trigger_api.py
netilion_lab_api/api/connected_asset_status_api.py
netilion_lab_api/api/document_standard_api.py
netilion_lab_api/api/mail_api.py
netilion_lab_api/api/recipe_api.py
netilion_lab_api/api/recipe_status_api.py
netilion_lab_api/api/recipe_type_api.py
netilion_lab_api/api/sim_card_api.py
netilion_lab_api/api/system_api.py
netilion_lab_api/api/system_status_api.py
netilion_lab_api/api/system_type_api.py
netilion_lab_api/api/value_objects_api.py
netilion_lab_api/models/__init__.py
netilion_lab_api/models/add_on_base.py
netilion_lab_api/models/add_on_request.py
netilion_lab_api/models/add_on_response.py
netilion_lab_api/models/add_ons_response.py
netilion_lab_api/models/app_instance_base.py
netilion_lab_api/models/app_instance_request.py
netilion_lab_api/models/app_instance_response.py
netilion_lab_api/models/app_instances_response.py
netilion_lab_api/models/asset_base.py
netilion_lab_api/models/asset_ids.py
netilion_lab_api/models/asset_key_value_objects_data.py
netilion_lab_api/models/asset_key_value_objects_response.py
netilion_lab_api/models/asset_key_values_data.py
netilion_lab_api/models/asset_key_values_response.py
netilion_lab_api/models/asset_response.py
netilion_lab_api/models/asset_value.py
netilion_lab_api/models/asset_value_object_request.py
netilion_lab_api/models/asset_value_object_request_data.py
netilion_lab_api/models/asset_value_objects_pagination.py
netilion_lab_api/models/asset_value_objects_request.py
netilion_lab_api/models/asset_values_pagination.py
netilion_lab_api/models/asset_values_response.py
netilion_lab_api-1.0.4.dist-info/LICENSE
netilion_lab_api-1.0.4.dist-info/METADATA
netilion_lab_api-1.0.4.dist-info/WHEEL
netilion_lab_api-1.0.4.dist-info/top_level.txt
netilion_lab_api-1.0.4.dist-info/RECORD
