Metadata-Version: 2.1
Name: netilion-lab-api
Version: 1.0.4
Summary: Client for accessing Netilion cloud (LAB)
Author-email: Tobias Schäuble <tobias.schaeuble@endress.com>
License: Copyright (c) 2018 The Python Packaging Authority
Project-URL: Homepage, https://staging-env.netilion.endress.com/
Project-URL: API, https://api.staging-env.netilion.endress.com/doc/v1/
Keywords: Netilion,Cloud,IIoT,Automation,E+H,Endress+Hauser
Classifier: Programming Language :: Python :: 3
Classifier: License :: OSI Approved :: MIT License
Classifier: Operating System :: OS Independent
Requires-Python: >=3.4
License-File: LICENSE
Requires-Dist: six
Requires-Dist: urllib3
Requires-Dist: requests-oauthlib
Requires-Dist: certifi
Requires-Dist: python-dateutil
Requires-Dist: setuptools
Requires-Dist: coverage
Requires-Dist: nose
Requires-Dist: pluggy
Requires-Dist: py
Requires-Dist: randomize
